setup.cfg
setup.py
Flask_Imgur.egg-info/PKG-INFO
Flask_Imgur.egg-info/SOURCES.txt
Flask_Imgur.egg-info/dependency_links.txt
Flask_Imgur.egg-info/not-zip-safe
Flask_Imgur.egg-info/requires.txt
Flask_Imgur.egg-info/top_level.txt
flask_imgur/flask_imgur.py