Metadata-Version: 1.1
Name: Flask-Imgur
Version: 0.1
Summary: Upload images straight to Imgur in your Flask app
Home-page: https://github.com/exaroth/flask-imgur
Author: Konrad Wasowicz
Author-email: exaroth@gmail.com
License: BSD
Platform: any
Classifier: Environment :: Web Environment
Classifier: Intended Audience :: Developers
Classifier: Operating System :: OS Independent
Classifier: Programming Language :: Python
Classifier: Topic :: Software Development :: Libraries :: Python Modules
